zhinst/comms/__init__.py
zhinst/comms/__init__.pyi
zhinst/comms/__main__.py
zhinst/comms/_comms.pyd
zhinst/comms/compiler.py
zhinst/comms/errors.pyi
zhinst/comms/py.typed
zhinst/comms/serialize.py
zhinst/comms/server.py
zhinst/comms/_comms/__init__.pyi
zhinst/comms/_comms/compiler.pyi
zhinst/comms/_comms/errors.pyi
zhinst/comms/_comms/serialize.pyi
zhinst/comms/capnp_schemas/capnp/c++.capnp
zhinst/comms/capnp_schemas/capnp/persistent.capnp
zhinst/comms/capnp_schemas/capnp/rpc-twoparty.capnp
zhinst/comms/capnp_schemas/capnp/rpc.capnp
zhinst/comms/capnp_schemas/capnp/schema.capnp
zhinst/comms/capnp_schemas/capnp/stream.capnp
zhinst/comms/capnp_schemas/capnp/compat/json.capnp
zhinst/comms/capnp_schemas/zhinst/io/protocol/capnp/common/client_id.capnp
zhinst/comms/capnp_schemas/zhinst/io/protocol/capnp/common/complex.capnp
zhinst/comms/capnp_schemas/zhinst/io/protocol/capnp/common/error.capnp
zhinst/comms/capnp_schemas/zhinst/io/protocol/capnp/common/hello_msg.capnp
zhinst/comms/capnp_schemas/zhinst/io/protocol/capnp/common/kwargs.capnp
zhinst/comms/capnp_schemas/zhinst/io/protocol/capnp/common/path.capnp
zhinst/comms/capnp_schemas/zhinst/io/protocol/capnp/common/result.capnp
zhinst/comms/capnp_schemas/zhinst/io/protocol/capnp/common/shf_vectors.capnp
zhinst/comms/capnp_schemas/zhinst/io/protocol/capnp/common/uuid.capnp
zhinst/comms/capnp_schemas/zhinst/io/protocol/capnp/common/value.capnp
zhinst/comms/capnp_schemas/zhinst/io/protocol/capnp/common/version.capnp
zhinst/comms/capnp_schemas/zhinst/io/protocol/capnp/reflection/reflection.capnp
zhinst_comms-3.3.0.2511263.dist-info/METADATA
zhinst_comms-3.3.0.2511263.dist-info/WHEEL
zhinst_comms-3.3.0.2511263.dist-info/licenses/LICENSE.txt
zhinst_comms-3.3.0.2511263.dist-info/RECORD
